MANIFEST.in
README.md
pytest.ini
setup.py
tox.ini
pyramid_backend/__init__.py
pyramid_backend/model.py
pyramid_backend/resources.py
pyramid_backend.egg-info/PKG-INFO
pyramid_backend.egg-info/SOURCES.txt
pyramid_backend.egg-info/dependency_links.txt
pyramid_backend.egg-info/not-zip-safe
pyramid_backend.egg-info/requires.txt
pyramid_backend.egg-info/top_level.txt
pyramid_backend/backend_manager/__init__.py
pyramid_backend/backend_manager/cqlengine.py
pyramid_backend/backend_manager/sqlalchemy.py
pyramid_backend/helpers/__init__.py
pyramid_backend/helpers/paginate.py
pyramid_backend/helpers/html/__init__.py
pyramid_backend/helpers/html/builder.py
pyramid_backend/templates/_layout.mak
pyramid_backend/templates/create.mak
pyramid_backend/templates/detail.mak
pyramid_backend/templates/index.mak
pyramid_backend/templates/list.mak
pyramid_backend/templates/no_schema.mak
pyramid_backend/templates/update.mak
pyramid_backend/views/__init__.py
pyramid_backend/views/model_view.py