Metadata-Version: 1.1
Name: pyramid-backend
Version: 1.3.1
Summary: pyramid_backend
Home-page: UNKNOWN
Author: Hoc .T Do
Author-email: hoc3010@gmail.com
License: UNKNOWN
Keywords: web wsgi bfg pylons pyramid
Platform: UNKNOWN
Classifier: Programming Language :: Python
Classifier: Framework :: Pyramid
Classifier: Topic :: Internet :: WWW/HTTP
Classifier: Topic :: Internet :: WWW/HTTP :: WSGI :: Application
